[
    {
        "title": "聚合图床",
        "icon": "聚合图床_icon.png",
        "url": "https://www.superbed.cn/",
        "description": "专业的图片托管与外链服务平台",
        "category": "图像视听"
    },
    {
        "title": "阿里巴巴矢量图标库",
        "icon": "阿里巴巴矢量图标库_icon.png",
        "url": "https://www.iconfont.cn/",
        "description": "国内功能强大且图标内容丰富的矢量图标库",
        "category": "图像视听"
    },
    {
        "title": "哲风壁纸",
        "icon": "哲风壁纸_icon.png",
        "url": "https://haowallpaper.com/",
        "description": "海量高分辨壁纸，提供从 4K 到 8K 的超清壁纸",
        "category": "图像视听"
    }
]